voxypy/__init__.py
voxypy/models.py
voxypy/numpy_vox_io/__init__.py
voxypy/numpy_vox_io/defaultpalette.py
voxypy/numpy_vox_io/models.py
voxypy/numpy_vox_io/parser.py
voxypy/numpy_vox_io/utils.py
voxypy/numpy_vox_io/writer.py
voxypy-0.2.3.dist-info/METADATA
voxypy-0.2.3.dist-info/WHEEL
voxypy-0.2.3.dist-info/top_level.txt
voxypy-0.2.3.dist-info/RECORD
