Metadata-Version: 2.1
Name: voxypy
Version: 0.2.3
Summary: Data structures for Voxel operations.
Home-page: https://gitlab.com/Claytone/voxypy
Author: Claytone
Author-email: clayton.wells.321@gmail.com
License: MIT
Platform: UNKNOWN
Classifier: License :: OSI Approved :: MIT License
Classifier: Programming Language :: Python :: 3
Classifier: Programming Language :: Python :: 3.7
Requires-Dist: numpy
Requires-Dist: Pillow
Requires-Dist: imageio
